twot/__init__.py
twot/classes.py
twot/examples.py
twot-0.0.4.dist-info/METADATA
twot-0.0.4.dist-info/WHEEL
twot-0.0.4.dist-info/licenses/LICENSE.md
twot-0.0.4.dist-info/RECORD
