Metadata-Version: 2.1
Name: twot
Version: 0.0.4
Summary: The Twitter Bot API - Tweet, Follow, Like, Retweet, and more with Python without using Twitter's API
Project-URL: Homepage, https://github.com/gpl27/twot
Project-URL: Bug Tracker, https://github.com/gpl27/twot/issues
Author-email: gpl27 <gpl27.dev@gmail.com>
License-File: LICENSE.md
Keywords: twitter,twitter-api,twitter-bot
Classifier: License :: OSI Approved :: MIT License
Classifier: Operating System :: OS Independent
Classifier: Programming Language :: Python :: 3
Requires-Python: >=3.7
Requires-Dist: selenium>=4.0.0
Requires-Dist: webdriver-manager==3.8.5
